MMDGraph/MMD.py
MMDGraph/MONK.py
MMDGraph/__init__.py
MMDGraph/glasso.py
MMDGraph/kernels/DeepKernel.py
MMDGraph/kernels/GNTK.py
MMDGraph/kernels/RandomWalk.py
MMDGraph/kernels/WL.py
MMDGraph/kernels/WWL.py
MMDGraph/kernels/__init__.py
mmdgraph-0.0.1.dist-info/METADATA
mmdgraph-0.0.1.dist-info/WHEEL
mmdgraph-0.0.1.dist-info/RECORD
