Metadata-Version: 2.1
Name: MMDGraph
Version: 0.0.1
Summary: A package for comparing two-sample of graphs
Author: Gareth W. Peters
Author-email: "Ragnar L. Gudmundarson" <ragnarlevigud@gmail.com>
Classifier: License :: OSI Approved :: MIT License
Classifier: Operating System :: OS Independent
Classifier: Programming Language :: Python :: 3
Requires-Python: >=3.7
Requires-Dist: networkx>=2.7.1
Requires-Dist: numpy~=1.21.0
Requires-Dist: scikit-learn>=1.0.2
Requires-Dist: scipy>=1.8.0
Requires-Dist: tqdm>=4.63.1
